{
    "antThalRadiation": 
        {
            "seed_images": ["thalamus"],
            "include_ordered" : ["AntLimbIntCapsule", "frontal-lobe"],
            "stop" : false,
            "act" : true
        },
    "postThalRadiation-parital": 
        {
            "seed_images": ["thalamus"],
            "include_ordered" : ["PostLimbIntCapsule", "parietal-lobe"],
            "exclude" : ["VLa", "VLp"],
            "stop" : false,
            "act" : true,
            "angle" : 10
        },
    "postThalRadiation-occipital": 
        {
            "seed_images": ["thalamus"],
            "include_ordered" : ["PostLimbIntCapsule", "occipital-lobe"],
            "exclude" : ["VLa", "VLp", "plane1-SLF1"],
            "stop" : false,
            "act" : true,
            "angle" : 10
        },
    "supThalRadiation": 
        {
            "seed_images": ["thalamus"],
            "include_ordered" : ["PostLimbIntCapsule", "gyrus-central"],
            "stop" : false,
            "act" : true
        },
    "infThalRadiation-insula": 
        {
            "seed_images": ["thalamus"],
            "include_ordered" : ["RetroLenticularIntCapsule", "plane-insula", "insula"],
            "exclude" : ["MGN", "temporal-lobe-dilated-1", "parietal-lobe-dilated-1", "gyrus-central-dilated-1", "frontal-lobe-dilated-1", "supramarginal-dilated-1", "brainStem"],
            "stop" : false,
            "act" : true
        },
        
    "inf-longi-fasci":
        { 
            "seed_images" : ["occipital-lobe"],
            "include" : ["temporal-lobe"],
            "masks" : ["cerebral-white-matter", "occipital-lobe", "temporal-lobe"],
            "exclude" : ["frontal-lobe-dilated-1", "parietal-lobe-dilated-1", "gyrus-central-dilated-1"],
            "angle" : 10,
            "stop" : false,
            "act" : true
        },
    
    "fornix":
        {
            "seed_images" : ["plane-mammillary-body"],
            "include_ordered" : ["plane-ort-fornix", "plane-fornix", "hippocampus"],
            "exclude" : ["Thalamus-eroded-1", "Lateral-Ventricle-eroded-1"]
        }
}